mcp_server/__init__.py
mcp_server/server.py
mcp_server/api_clients/__init__.py
mcp_server/api_clients/github_client.py
mcp_server/api_clients/slack_client.py
mcp_server/auth/__init__.py
mcp_server/auth/credentials.py
mcp_server/auth/device_flow.py
mcp_server/resources/__init__.py
mcp_server/resources/github_resources.py
mcp_server/resources/slack_resources.py
mcp_server/tools/__init__.py
mcp_server/tools/auth_tools.py
mcp_server/tools/git_tools.py
mcp_server/tools/github_tools.py
mcp_server/tools/slack_tools.py
mcp_server/tools/utility_tools.py
quickcall_integrations-0.3.9.dist-info/METADATA
quickcall_integrations-0.3.9.dist-info/WHEEL
quickcall_integrations-0.3.9.dist-info/entry_points.txt
quickcall_integrations-0.3.9.dist-info/RECORD
