Metadata-Version: 2.4
Name: quickcall-integrations
Version: 0.3.9
Summary: MCP server with developer integrations for Claude Code and Cursor
Requires-Python: >=3.10
Requires-Dist: fastmcp>=2.13.0
Requires-Dist: httpx>=0.28.0
Requires-Dist: pydantic>=2.11.7
Requires-Dist: pygithub>=2.8.1
Requires-Dist: pyyaml>=6.0
Requires-Dist: rapidfuzz>=3.0.0
